begemot/__init__.py
begemot/__main__.py
begemot/analysers/lexer.py
begemot/analysers/parser.py
begemot/boxes/integer.py
begemot/components/math.c
begemot/components/math.h
begemot/console.py
begemot/constants.py
begemot/modules/math.py
begemot/tokens.py
begemot-0.1.0.dist-info/LICENSE
begemot-0.1.0.dist-info/METADATA
begemot-0.1.0.dist-info/WHEEL
begemot-0.1.0.dist-info/entry_points.txt
begemot-0.1.0.dist-info/RECORD
