Metadata-Version: 2.1
Name: begemot
Version: 0.1.0
Summary: begemot — Compiled programming language in Mongolian
License: Apache-2.0
Author: mmlvgx
Author-email: mmlvgx@gmail.com
Requires-Python: >=3.10,<4.0
Classifier: License :: OSI Approved :: Apache Software License
Classifier: Programming Language :: Python :: 3
Classifier: Programming Language :: Python :: 3.10
Classifier: Programming Language :: Python :: 3.11
